brain_region_signal_statistics_calculalor.py
brain_region_signal_statistics_calculalor-0.0.2.dist-info/METADATA
brain_region_signal_statistics_calculalor-0.0.2.dist-info/WHEEL
brain_region_signal_statistics_calculalor-0.0.2.dist-info/top_level.txt
brain_region_signal_statistics_calculalor-0.0.2.dist-info/RECORD
