Metadata-Version: 2.1
Name: brain-region-signal-statistics-calculalor
Version: 0.0.2
Summary: Compute brain region signal statistics for 3D brain volume
Home-page: https://github.com/daisydiwang/brain_region_signal_statistics_calculalor
Author: Di Wang
Author-email: di-wang@uiowa.edu
Keywords: 3D brain image,statistics,hierarchical structure
Classifier: Intended Audience :: Science/Research
Classifier: Programming Language :: Python :: 3
Requires-Dist: numpy
Requires-Dist: pandas
